{"nodes": [{"id": "d_projects_wasif_portfolio_src_utility_cursor_trail_ts", "label": "cursor-trail.ts", "file_type": "code", "source_file": "D:\\Projects\\Wasif Portfolio\\src\\utility\\cursor-trail.ts", "source_location": "L1"}, {"id": "utility_cursor_trail_cursortrail", "label": "cursorTrail()", "file_type": "code", "source_file": "D:\\Projects\\Wasif Portfolio\\src\\utility\\cursor-trail.ts", "source_location": "L8"}], "edges": [{"source": "d_projects_wasif_portfolio_src_utility_cursor_trail_ts", "target": "react", "relation": "imports_from", "confidence": "EXTRACTED", "source_file": "D:\\Projects\\Wasif Portfolio\\src\\utility\\cursor-trail.ts", "source_location": "L1", "weight": 1.0}, {"source": "d_projects_wasif_portfolio_src_utility_cursor_trail_ts", "target": "utility_cursor_trail_cursortrail", "relation": "contains", "confidence": "EXTRACTED", "source_file": "D:\\Projects\\Wasif Portfolio\\src\\utility\\cursor-trail.ts", "source_location": "L8", "weight": 1.0}], "raw_calls": [{"caller_nid": "utility_cursor_trail_cursortrail", "callee": "getPropertyValue", "is_member_call": true, "source_file": "D:\\Projects\\Wasif Portfolio\\src\\utility\\cursor-trail.ts", "source_location": "L9"}, {"caller_nid": "utility_cursor_trail_cursortrail", "callee": "getComputedStyle", "is_member_call": false, "source_file": "D:\\Projects\\Wasif Portfolio\\src\\utility\\cursor-trail.ts", "source_location": "L9"}, {"caller_nid": "utility_cursor_trail_cursortrail", "callee": "join", "is_member_call": true, "source_file": "D:\\Projects\\Wasif Portfolio\\src\\utility\\cursor-trail.ts", "source_location": "L13"}, {"caller_nid": "utility_cursor_trail_cursortrail", "callee": "split", "is_member_call": true, "source_file": "D:\\Projects\\Wasif Portfolio\\src\\utility\\cursor-trail.ts", "source_location": "L13"}, {"caller_nid": "utility_cursor_trail_cursortrail", "callee": "getContext", "is_member_call": true, "source_file": "D:\\Projects\\Wasif Portfolio\\src\\utility\\cursor-trail.ts", "source_location": "L16"}]}